setup.py
setuptools_webdav.py
setuptools_webdav.egg-info/PKG-INFO
setuptools_webdav.egg-info/SOURCES.txt
setuptools_webdav.egg-info/dependency_links.txt
setuptools_webdav.egg-info/entry_points.txt
setuptools_webdav.egg-info/requires.txt
setuptools_webdav.egg-info/top_level.txt