Metadata-Version: 1.1
Name: setuptools-webdav
Version: 0.0.1
Summary: Setuptools/distribute plugin for uploading to webdav servers
Home-page: https://bitbucket.org/mneagul/setuptools-webdav
Author: Marian Neagul
Author-email: marian@ieat.ro
License: APL
Keywords: setuptools
Platform: UNKNOWN
Classifier: Intended Audience :: Developers
Classifier: Development Status :: 3 - Alpha
Classifier: Framework :: Setuptools Plugin
Classifier: Operating System :: OS Independent
Classifier: License :: OSI Approved :: Apache Software License
